{
  "categorias": [
    {
      "titulo": "Ciências da natureza e suas tecnologias",
      "link": "https://www.alura.com.br/formacao-front-end",
      "cor": "#6BD1FF",
      "link_extra": {
        "text": "É legal, mas..."
      },
      "videos": [
        {
          "titulo": "A Lei ZERO da Termodinâmica",
          "url": "https://www.youtube.com/watch?v=8fo8_m-qP9M"
        },
        {
          "titulo": "REFRAÇÃO - PARTE 01 - Física com Montalvão",
          "url": "https://www.youtube.com/watch?v=qEktm4ji5ak"
        },
        {
          "titulo": "Seria possível parar um furacão com uma bomba atômica? | Nerdologia",
          "url": "https://www.youtube.com/watch?v=4p8mnKy7GxA"
        },
        {
          "titulo": "A transmutação humana de Fullmetal Alchemist | Nerdologia",
          "url": "https://youtu.be/DYlScWkjE_g"
        },
        {
          "titulo": "Membrana Plasmática | Célula | Prof. Paulo Jubilut",
          "url": "https://youtu.be/yaiEgmOboq0"
        },
        {
          "titulo": "MITOSE | Divisão Celular | Professor Jubilut",
          "url": "https://youtu.be/zvr7O5tqNiY"
        },
        {
          "titulo": "ENERGIA - Física com Montalvão",
          "url": "https://youtu.be/hLYC5aWK1bw"
        }
      ]
    },
    {
      "titulo": "Linguagens, códigos e suas tecnologias",
      "cor": "#00C86F",
      "link_extra": {
        "text": "Eh nois!!!"
      },
      "videos": [
        {
          "titulo": "Transitividade Verbal [Prof Noslen]",
          "url": "https://youtu.be/y2haxLgR4BM"
        },
        {
          "titulo": "Sintaxe do Verbo [Prof Noslen]",
          "url": "https://youtu.be/uPoNVpFf4FQ"
        }
      ]
    },
    {
      "titulo": "Matemática e suas tecnologias",
      "cor": "#9cd33b",
      "link_extra": {
        "text": "DMA te espera."
      },
      "videos": [
        {
          "titulo": "Potências - Qual é o maior?",
          "url": "https://youtu.be/SizUrDi-keo"
        },
        {
          "titulo": "Potência de Ponto - Segmentos em uma circunferência",
          "url": "https://youtu.be/KcBBhcq2800"
        },
        {
          "titulo": "Conceitos Básicos - Matemática Financeira #1",
          "url": "https://www.youtube.com/watch?v=vxKV2UZkKm8"
        },
        {
          "titulo": "Razões Trigonométricas (seno, cosseno e tangente) - Trigonometria no Triângulo Retângulo",
          "url": "https://youtu.be/4sTUs4ll3dI"
        }
      ]
    },
    {
      "titulo": "Ciências humanas e suas tecnologias",
      "cor": "orange",
      "link_extra": {
        "text": "A culpa é dos Portugueses."
      },
      "videos": [
        {
          "titulo": "500 Anos em 1 Hora / História do Brasil",
          "url": "https://youtu.be/q7E4XrfGGnE"
        },
        {
          "titulo": "Geografia pro Enem - O que é Espaço Geográfico? Lugar, Paisagem, Região e Território.",
          "url": "https://youtu.be/uWa2WLOveaQ"
        },
        {
          "titulo": "Enem 2019 | Revisão de Filosofia",
          "url": "https://youtu.be/EQsRh7X9n0E"
        }
      ]
    }
  ]
}